{
  "orgName": "TruStage D2C",
  "description": "Scratch org",
  "edition": "Enterprise",    
  "country": "US",
  "language": "en_US",
  "features": ["PersonAccounts"],  
  "settings": {
    "userManagementSettings": {
      "enableEnhancedPermsetMgmt": true,
      "enableNewProfileUI": true,
      "permsetsInFieldCreation": true     
    },
    "nameSettings":{
        "enableMiddleName": true,
        "enableNameSuffix": true
    },   
    "securitySettings": {
      "sessionSettings":{
        "forceRelogin": false      
      },
      "enableAdminLoginAsAnyUser": true
    }
  },
  "objectSettings": {
    "opportunity": {
      "sharingModel": "private",
      "defaultRecordType": "default"
    },
    "account": {
      "sharingModel": "private",
      "defaultRecordType": "default"
    },
    "contact": {
      "sharingModel": "private",
      "defaultRecordType": "default"
    },
    "campaign": {
      "sharingModel": "private",
      "defaultRecordType": "default"
    },
    "user": {
      "sharingModel": "private"
    }
  }
}  